zeonegraph/__init__.py
zeonegraph/_edge.py
zeonegraph/_graphid.py
zeonegraph/_graphpath.py
zeonegraph/_property.py
zeonegraph/_vertex.py
zeonegraph-2.1.0.dist-info/LICENSE
zeonegraph-2.1.0.dist-info/METADATA
zeonegraph-2.1.0.dist-info/WHEEL
zeonegraph-2.1.0.dist-info/top_level.txt
zeonegraph-2.1.0.dist-info/RECORD
