Metadata-Version: 2.1
Name: zeonegraph
Version: 2.1.0
Summary: Psycopg2 type extension module for ZeoneGraph
Author: zhangjianuxe
Author-email: zhangjianxue@zeonedb.com
Maintainer: zeone
Maintainer-email: zeone@zeonedb.com
License-File: LICENSE
Requires-Dist: psycopg2-binary >=2.7.4
